vidispine/__init__.py
vidispine/api_client.py
vidispine/configuration.py
vidispine/exceptions.py
vidispine/rest.py
vidispine/api/__init__.py
vidispine/api/access_api.py
vidispine/api/access_key_api.py
vidispine/api/analyze_api.py
vidispine/api/audit_log_api.py
vidispine/api/auto_import_api.py
vidispine/api/auto_projection_api.py
vidispine/api/autocomplete_api.py
vidispine/api/collection_api.py
vidispine/api/configuration_api.py
vidispine/api/conform_api.py
vidispine/api/cost_estimation_api.py
vidispine/api/dataset_api.py
vidispine/api/deletion_lock_api.py
vidispine/api/document_api.py
vidispine/api/eidr_api.py
vidispine/api/entity_site_rule_api.py
vidispine/api/entity_storage_rule_api.py
vidispine/api/export_location_api.py
vidispine/api/external_id_api.py
vidispine/api/external_id_namespace_api.py
vidispine/api/field_access_api.py
vidispine/api/field_group_access_api.py
vidispine/api/field_group_external_id_api.py
vidispine/api/file_api.py
vidispine/api/global_metadata_api.py
vidispine/api/group_api.py
vidispine/api/import_api.py
vidispine/api/import_settings_api.py
vidispine/api/item_api.py
vidispine/api/item_bulky_metadata_api.py
vidispine/api/item_lock_api.py
vidispine/api/javascript_api.py
vidispine/api/job_api.py
vidispine/api/library_api.py
vidispine/api/license_api.py
vidispine/api/loudness_api.py
vidispine/api/metadata_api.py
vidispine/api/metadata_field_api.py
vidispine/api/metadata_field_groups_api.py
vidispine/api/metadata_lock_api.py
vidispine/api/metadata_migration_api.py
vidispine/api/metadata_schema_api.py
vidispine/api/notification_api.py
vidispine/api/poster_resource_api.py
vidispine/api/project_collection_api.py
vidispine/api/project_version_api.py
vidispine/api/projection_api.py
vidispine/api/quota_rule_api.py
vidispine/api/reindex_api.py
vidispine/api/relation_api.py
vidispine/api/resource_api.py
vidispine/api/scheduled_request_api.py
vidispine/api/search_api.py
vidispine/api/selftest_api.py
vidispine/api/sequence_api.py
vidispine-5.0.4.dist-info/METADATA
vidispine-5.0.4.dist-info/WHEEL
vidispine-5.0.4.dist-info/top_level.txt
vidispine-5.0.4.dist-info/RECORD
