Metadata-Version: 2.1
Name: vidispine
Version: 5.0.4
Summary: Vidispine API
Home-page: UNKNOWN
Author: API support
Author-email: info@vidispine.com
License: UNKNOWN
Keywords: OpenAPI,OpenAPI-Generator,Vidispine API
Platform: UNKNOWN
Requires-Dist: urllib3 (>=1.15)
Requires-Dist: six (>=1.10)
Requires-Dist: certifi
Requires-Dist: python-dateutil
